{
  "accounts": [
    {
      "id": 1,
      "name": "Nguyễn Văn A",
      "email": "nguyenvana@example.com",
      "password": "Password123!"
    },
    {
      "id": 2,
      "name": "Trần Thị B",
      "email": "tranthib@example.com",
      "password": "SecurePass456$"
    },
    {
      "id": 3,
      "name": "Lê Hoàng C",
      "email": "lehoangc@example.com",
      "password": "MyFakePassword789"
    },
    {
      "id": 4,
      "name": "Phạm Văn D",
      "email": "phamvand@example.com",
      "password": "TestAccount@2026"
    },
    {
      "id": 5,
      "name": "Hoàng Thị E",
      "email": "hoangthie@example.com",
      "password": "DevPassWord#001"
    },
    {
      "id": 6,
      "name": "Vũ Quốc F",
      "email": "vuquocf@example.com",
      "password": "MockData!999"
    },
    {
      "id": 7,
      "name": "Đặng Ngọc G",
      "email": "dangngocg@example.com",
      "password": "DummyUser2026*"
    }
  ]
}
